b_node_cdk_layer/Dockerfile
b_node_cdk_layer/__init__.py
b_node_cdk_layer/node_cdk_layer.py
b_node_cdk_layer_test/integration/__init__.py
b_node_cdk_layer_test/integration/app.py
b_node_cdk_layer_test/integration/conftest.py
b_node_cdk_layer_test/integration/infra_create.py
b_node_cdk_layer_test/integration/infra_destroy.py
b_node_cdk_layer_test/integration/manager.py
b_node_cdk_layer_test/integration/fixtures/__init__.py
b_node_cdk_layer_test/integration/infrastructure/__init__.py
b_node_cdk_layer_test/integration/infrastructure/main_stack.py
b_node_cdk_layer_test/integration/infrastructure/lambda_source_code/__init__.py
b_node_cdk_layer_test/integration/infrastructure/lambda_source_code/index.py
b_node_cdk_layer_test/integration/tests/__init__.py
b_node_cdk_layer_test/integration/tests/test_layer.py
b_node_cdk_layer-0.1.0.dist-info/LICENSE
b_node_cdk_layer-0.1.0.dist-info/METADATA
b_node_cdk_layer-0.1.0.dist-info/WHEEL
b_node_cdk_layer-0.1.0.dist-info/top_level.txt
b_node_cdk_layer-0.1.0.dist-info/RECORD
