Metadata-Version: 2.1
Name: b-node-cdk-layer
Version: 0.1.0
Summary: AWS CDK lambda layer resource that contains node and aws cdk cli packages.
Home-page: https://github.com/biomapas/B.NodeCdkLayer.git
License: Apache License 2.0
Keywords: AWS CDK Lambda Layer Node
Platform: UNKNOWN
Classifier: Programming Language :: Python :: 3
Classifier: Operating System :: OS Independent
License-File: LICENSE
Requires-Dist: aws-cdk.core (>=1.100.0)
Requires-Dist: aws-cdk.aws-lambda (>=1.100.0)
